dbt_opiner/__init__.py
dbt_opiner/cli.py
dbt_opiner/config_singleton.py
dbt_opiner/dbt.py
dbt_opiner/entrypoint.py
dbt_opiner/file_handlers.py
dbt_opiner/git.py
dbt_opiner/linter.py
dbt_opiner/opinions/BQ001_bigquery_targets_must_have_maximum_bytes_billed.py
dbt_opiner/opinions/BQ002_bigquery_tables_should_have_clustering.py
dbt_opiner/opinions/BQ003_bigquery_views_must_have_partition_and_cluster_description.py
dbt_opiner/opinions/BQ004_bigquery_models_must_persist_docs.py
dbt_opiner/opinions/D001_yaml_docs_should_have_n_docs.py
dbt_opiner/opinions/L001_sources_must_only_be_used_in_staging.py
dbt_opiner/opinions/L002_layer_x_must_not_select_from_layer_y.py
dbt_opiner/opinions/O001_model_must_have_description.py
dbt_opiner/opinions/O002_model_description_must_have_keywords.py
dbt_opiner/opinions/O003_all_columns_must_have_description.py
dbt_opiner/opinions/O004_final_columns_in_model_must_be_explicitly_named_at_least_once.py
dbt_opiner/opinions/O005_model_should_have_unique_key.py
dbt_opiner/opinions/O006_models_names_must_start_with_a_prefix.py
dbt_opiner/opinions/O007_yml_files_must_not_have_outdated_colums.py
dbt_opiner/opinions/P001_pii_columns_must_have_tags.py
dbt_opiner/opinions/P002_project_must_not_send_anon_stats.py
dbt_opiner/opinions/__init__.py
dbt_opiner/opinions/base_opinion.py
dbt_opiner/opinions/opinions_pack.py
dbt_opiner/package.py
dbt_opiner-1.5.0.dist-info/LICENSE
dbt_opiner-1.5.0.dist-info/METADATA
dbt_opiner-1.5.0.dist-info/WHEEL
dbt_opiner-1.5.0.dist-info/entry_points.txt
dbt_opiner-1.5.0.dist-info/RECORD
