Metadata-Version: 2.3
Name: dbt-opiner
Version: 1.5.0
Summary: A tool to keep dbt projects on rails
License: MIT
Author: Rodrigo Loredo
Author-email: loredo.rod@gmail.com
Requires-Python: >=3.10,<3.13
Classifier: License :: OSI Approved :: MIT License
Classifier: Programming Language :: Python :: 3
Classifier: Programming Language :: Python :: 3.10
Classifier: Programming Language :: Python :: 3.11
Classifier: Programming Language :: Python :: 3.12
Requires-Dist: click (>=8.1)
Requires-Dist: loguru (>=0.7.2,<0.8.0)
Requires-Dist: pandas (>=2.2.2,<3.0.0)
Requires-Dist: pyfiglet (>=1.0.2,<2.0.0)
Requires-Dist: pyyaml (>=6.0.1,<7.0.0)
Requires-Dist: requests (>=2.32.3,<3.0.0)
Requires-Dist: setuptools (>=72.1.0,<73.0.0)
Requires-Dist: sqlglot (>=25.10.0,<26.0.0)
Requires-Dist: tabulate (>=0.9.0,<0.10.0)
